aws_sdk_python/__init__.py
aws_sdk_python-0.1.2.dist-info/METADATA
aws_sdk_python-0.1.2.dist-info/WHEEL
aws_sdk_python-0.1.2.dist-info/licenses/LICENSE
aws_sdk_python-0.1.2.dist-info/licenses/NOTICE
aws_sdk_python-0.1.2.dist-info/RECORD
